[{"Von": "16:15", "Bis": "17:15", "Saal": 6, "Name": "HipHop 2008 - 2011", "Lehrer": "Linda Ritter"}, {"Von": "17:15", "Bis": "18:15", "Saal": 1, "Name": "Formationen<br>J2 und Adults ", "Lehrer": "Ryu Oozaru"}, {"Von": "18:25", "Bis": "19:25", "Saal": 1, "Name": "Zumba<br> MasterClass", "Lehrer": "Claudia Ritter"}, {"Von": "19:45", "Bis": "20:55", "Saal": 1, "Name": "Paartanz", "Lehrer": "Christopher Bischoff"}, {"Von": "21:00", "Bis": "22:10", "Saal": 1, "Name": "Paartanz", "Lehrer": "Christopher Bischoff"}]